Metadata-Version: 2.1
Name: package-creation-tutorial
Version: 1.0
Summary: 
Author: brash6
Author-email: hadrienmariaccia@gmail.com
Requires-Python: >=3.10,<3.13
Classifier: Programming Language :: Python :: 3
Classifier: Programming Language :: Python :: 3.10
Classifier: Programming Language :: Python :: 3.11
Classifier: Programming Language :: Python :: 3.12
Requires-Dist: numpy (>=2.0.0,<3.0.0)
Requires-Dist: pandas (>=2.2.2,<3.0.0)
Requires-Dist: pre-commit (>=3.7.1,<4.0.0)
Requires-Dist: pytest (>=8.2.2,<9.0.0)
Requires-Dist: pytest-cov (>=5.0.0,<6.0.0)
Requires-Dist: ruff (>=0.5.0,<0.6.0)
Requires-Dist: sphinx (>=7.3.7,<8.0.0)
Requires-Dist: sphinx-rtd-theme (>=2.0.0,<3.0.0)
